cad_tickers/__init__.py
cad_tickers/exchanges/__init__.py
cad_tickers/exchanges/all_tickers.py
cad_tickers/exchanges/classes.py
cad_tickers/exchanges/cse.py
cad_tickers/exchanges/tsx/__init__.py
cad_tickers/exchanges/tsx/get_ticker_data.py
cad_tickers/exchanges/tsx/get_tickers.py
cad_tickers/exchanges/tsx/gql_data.py
cad_tickers/news/__init__.py
cad_tickers/news/ceo/__init__.py
cad_tickers/news/ceo/main.py
cad_tickers/news/ceo/scrap.py
cad_tickers/news/ceo/spiel_class.py
cad_tickers/news/ceo/utils.py
cad_tickers/news/iiroc_halts.py
cad_tickers/news/stock_news.py
cad_tickers/sedar/__init__.py
cad_tickers/sedar/cse.py
cad_tickers/sedar/tsx.py
cad_tickers/test.py
cad_tickers/util/__init__.py
cad_tickers/util/utils.py
cad_tickers-1.5.4.dist-info/LICENSE
cad_tickers-1.5.4.dist-info/WHEEL
cad_tickers-1.5.4.dist-info/METADATA
cad_tickers-1.5.4.dist-info/RECORD
