Metadata-Version: 2.1
Name: cad-tickers
Version: 1.5.4
Summary: Various Stock Utilties Created by me
Home-page: https://github.com/FriendlyUser/cad_tickers
License: MIT
Keywords: Poetry,Stock Tickers,Requests,CSE,TSX
Author: David Li
Author-email: davidli012345@gmail.com
Maintainer: David Li
Maintainer-email: davidli012345@gmail.com
Requires-Python: >=3.7.1,<4.0.0
Classifier: License :: OSI Approved :: MIT License
Classifier: Programming Language :: Python :: 3
Classifier: Programming Language :: Python :: 3.10
Classifier: Programming Language :: Python :: 3.8
Classifier: Programming Language :: Python :: 3.9
Requires-Dist: beautifulsoup4 (>=4.9.1,<5.0.0)
Requires-Dist: coverage (>=5.2,<6.0)
Requires-Dist: lxml (>=4.5.2,<5.0.0)
Requires-Dist: openpyxl (>=3.0.7,<4.0.0)
Requires-Dist: pandas (>=1.3.0,<2.0.0)
Requires-Dist: random-user-agent (>=1.0.1,<2.0.0)
Requires-Dist: requests (>=2.24.0,<3.0.0)
Requires-Dist: xlrd (>=1.2.0,<2.0.0)
Project-URL: Documentation, https://readthedocs.org/projects/cad-tickers/
Project-URL: Repository, https://github.com/FriendlyUser/cad_tickers
